<?xml version="1.0" encoding="UTF-8"?><root><scenarios><scenario enableipspoofing="False" id="550" name="SBNT_PT_1"><script id="447" name="SBNTest_AllOptions"><setting browsercache="false" currentloadgenid="1" durationmode="1" durationtime="0;10;0" incrementtime="0;0;10" incrementuser="1" iterations="2" maxuser="10" parallelconnections="6" startuser="1" startuserid="0" totalloadgen="1" type="2"/></script></scenario><scenario enableipspoofing="False" id="551" name="SBNT_50User_30mins_1"><script id="447" name="SBNTest_AllOptions"><setting browsercache="false" currentloadgenid="1" durationmode="1" durationtime="0;30;0" incrementtime="0;0;10" incrementuser="5" iterations="1" maxuser="25" parallelconnections="6" startuser="1" startuserid="0" totalloadgen="1" type="2"/></script></scenario></scenarios></root>