<?xml version="1.0" encoding="UTF-8"?><root><scenarios><scenario enableipspoofing="False" id="1426930869830" name="youtubesearch1"><script id="1426930869825" name="youtubesearch"><setting browsercache="false" currentloadgenid="1" durationtime="0;3;0" incrementtime="0;0;1" incrementuser="1" iterations="1" maxuser="5" startuser="5" startuserid="0" totalloadgen="1" type="1"/></script></scenario><scenario enableipspoofing="False" id="134" name="adactin_hotel_reservation"><script id="104" name="searchadactin"><setting browsercache="false" currentloadgenid="1" durationtime="0;1;0" incrementtime="0;0;0" incrementuser="1" iterations="1" maxuser="1" startuser="1" startuserid="0" totalloadgen="1" type="1"/></script></scenario><scenario enableipspoofing="False" id="135" name="youtubesearch"><script id="105" name="youtubesearch"><setting browsercache="false" currentloadgenid="1" durationtime="0;1;0" incrementtime="0;0;0" incrementuser="1" iterations="1" maxuser="1" startuser="1" startuserid="0" totalloadgen="1" type="1"/></script></scenario></scenarios></root>